sec_edgar_mcp/__init__.py
sec_edgar_mcp/config.py
sec_edgar_mcp/document_parser.py
sec_edgar_mcp/server.py
sec_edgar_mcp/core/__init__.py
sec_edgar_mcp/core/client.py
sec_edgar_mcp/core/models.py
sec_edgar_mcp/tools/__init__.py
sec_edgar_mcp/tools/company.py
sec_edgar_mcp/tools/filings.py
sec_edgar_mcp/tools/financial.py
sec_edgar_mcp/tools/insider.py
sec_edgar_mcp/tools/insider_complex.py
sec_edgar_mcp/tools/types.py
sec_edgar_mcp/utils/__init__.py
sec_edgar_mcp/utils/cache.py
sec_edgar_mcp/utils/constants.py
sec_edgar_mcp/utils/exceptions.py
sec_edgar_mcp-1.0.8.dist-info/licenses/AUTHORS
sec_edgar_mcp-1.0.8.dist-info/licenses/LICENSE
sec_edgar_mcp-1.0.8.dist-info/METADATA
sec_edgar_mcp-1.0.8.dist-info/WHEEL
sec_edgar_mcp-1.0.8.dist-info/entry_points.txt
sec_edgar_mcp-1.0.8.dist-info/top_level.txt
sec_edgar_mcp-1.0.8.dist-info/RECORD
