Metadata-Version: 2.4
Name: sec-edgar-mcp
Version: 1.0.8
Summary: SEC EDGAR MCP server for company filings and financial data
Author-email: Stefano Amorelli <stefano@amorelli.tech>
License: AGPL-3.0
Project-URL: Homepage, https://github.com/stefanoamorelli/sec-edgar-mcp
Project-URL: Bug Tracker, https://github.com/stefanoamorelli/sec-edgar-mcp/issues
Classifier: Programming Language :: Python :: 3
Classifier: License :: OSI Approved :: GNU Affero General Public License v3
Classifier: Operating System :: OS Independent
Requires-Python: >=3.11
License-File: LICENSE
License-File: AUTHORS
Requires-Dist: mcp[cli]>=1.7.1
Requires-Dist: edgartools>=4.4.0
Requires-Dist: requests>=2.31.0
Provides-Extra: dev
Requires-Dist: ruff>=0.1.14; extra == "dev"
Requires-Dist: mypy>=1.8; extra == "dev"
Dynamic: license-file
